passwords_access/__init__.py
passwords_access/__main__.py
passwords_access/auth.py
passwords_access/caller.py
passwords_access/config.py
passwords_access/py.typed
passwords_access/dataclasses/__init__.py
passwords_access/dataclasses/caller_props.py
passwords_access-1.1.0.dist-info/METADATA
passwords_access-1.1.0.dist-info/WHEEL
passwords_access-1.1.0.dist-info/entry_points.txt
passwords_access-1.1.0.dist-info/licenses/LICENSE
passwords_access-1.1.0.dist-info/RECORD
