Metadata-Version: 2.3
Name: passwords_access
Version: 1.1.0
Summary: Simple library to retrieve secrets from server
Project-URL: Homepage, https://github.com/dmitriyVasilievich1986/passwords_access
Author-email: dmitriyvasil@gmail.com
Maintainer-email: dmitriyvasil@gmail.com
License: MIT License
Keywords: api,encryption,password
Classifier: Intended Audience :: Developers
Classifier: License :: OSI Approved :: MIT License
Classifier: Programming Language :: Python :: 3
Classifier: Programming Language :: Python :: 3.9
Classifier: Programming Language :: Python :: 3.10
Classifier: Programming Language :: Python :: 3.11
Classifier: Programming Language :: Python :: 3.12
Requires-Python: <3.13,>=3.9
Requires-Dist: click>=8.0.3
Requires-Dist: python-dotenv
Requires-Dist: requests>=2.0
